mfdev_scraper_sdk/__init__.py
mfdev_scraper_sdk/errors.py
mfdev_scraper_sdk/library.py
mfdev_scraper-0.1.6.dist-info/METADATA
mfdev_scraper-0.1.6.dist-info/WHEEL
mfdev_scraper-0.1.6.dist-info/licenses/LICENSE
mfdev_scraper-0.1.6.dist-info/RECORD
