Metadata-Version: 2.4
Name: mfdev_scraper
Version: 0.1.6
Summary: A lightweight Python SDK for web scraping, data cleaning, and CSV/Excel export.
Project-URL: Homepage, https://mfdev.vercel.app
Project-URL: Source, https://github.com/Fer-Mig-Agus/MFDev-Scraper-SDK
Author: Miguel Fernandez
License: MIT
License-File: LICENSE
Keywords: scraper
Requires-Python: >=3.10
Requires-Dist: curl-cffi==0.13.0
Requires-Dist: openpyxl==3.1.5
Requires-Dist: pandas==2.3.2
Provides-Extra: dev
Requires-Dist: build; extra == 'dev'
Requires-Dist: pytest; extra == 'dev'
Requires-Dist: twine; extra == 'dev'
